matgen_rester/MatgenError.py
matgen_rester/__init__.py
matgen_rester/args.py
matgen_rester/auth.py
matgen_rester/matdata.py
matgen_rester/matgenrester.py
matgen_rester/figure/__Init__.py
matgen_rester/figure/test1.py
matgen_rester/structure_properties/MatgenError.py
matgen_rester/structure_properties/__init__.py
matgen_rester/structure_properties/band_structure.py
matgen_rester/structure_properties/cell.py
matgen_rester/structure_properties/conventional_cell_site.py
matgen_rester/structure_properties/density_of_states.py
matgen_rester/structure_properties/elastic_property.py
matgen_rester/structure_properties/magnetization.py
matgen_rester/structure_properties/primitive_cell_site.py
matgen_rester/tests/__init__.py
matgen_rester/tests/test_rester.py
matgen_rester-2.5.0.dist-info/LICENSE
matgen_rester-2.5.0.dist-info/METADATA
matgen_rester-2.5.0.dist-info/WHEEL
matgen_rester-2.5.0.dist-info/top_level.txt
matgen_rester-2.5.0.dist-info/RECORD
