Metadata-Version: 2.1
Name: matgen-rester
Version: 2.5.0
Summary: A python wrapper for matgen dft API
Home-page: https://github.com
Author: nscc.gz
Author-email: "nscc.gz" <matgen@nscc-gz.cn>
License: MIT
Project-URL: Homepage, https://pypi.org/manage/project/matgen-rester
Project-URL: Bug Tracker, https://pypi.org/manage/project/matgen-rester/issues
Classifier: Programming Language :: Python :: 3
Classifier: License :: OSI Approved :: MIT License
Classifier: Operating System :: OS Independent
Requires-Python: >=3.7
License-File: LICENSE
Requires-Dist: PyYaml
Requires-Dist: numpy
Requires-Dist: requests
